README.md
setup.py
stylelens_product/__init__.py
stylelens_product/crawls.py
stylelens_product/database.py
stylelens_product/hosts.py
stylelens_product/models.py
stylelens_product/products.py
stylelens_product/versions.py
stylelens_product.egg-info/PKG-INFO
stylelens_product.egg-info/SOURCES.txt
stylelens_product.egg-info/dependency_links.txt
stylelens_product.egg-info/requires.txt
stylelens_product.egg-info/top_level.txt
stylelens_product/bigquery/__init__.py
stylelens_product/bigquery/amazon_search_keywords.py
stylelens_product/bigquery/database.py
stylelens_product/bigquery/products.py
test/__init__.py
test/test_feedback.py
test/test_host.py
test/test_host_api.py
test/test_image.py
test/test_object.py
test/test_product.py
test/test_version.py
test/test_writer.py