Metadata-Version: 1.0
Name: stylelens-product
Version: 1.0.93
Summary: bl-db-product
Home-page: UNKNOWN
Author: UNKNOWN
Author-email: master@bluehack.net
License: UNKNOWN
Keywords: BlueLens,bl-db-product
Platform: UNKNOWN
